druglikeness/__init__.py
druglikeness/deepdl/__init__.py
druglikeness/deepdl/model.py
druglikeness/deepdl/vocab.py
druglikeness/deepdl/train_utils/config.py
druglikeness/deepdl/train_utils/dataset.py
druglikeness/deepdl/train_utils/module.py
druglikeness/deepdl/train_utils/train.py
druglikeness/deepdl/train_utils/utils.py
druglikeness/sdk/__init__.py
druglikeness/sdk/api.py
druglikeness-0.2.2.dist-info/licenses/LICENSE
druglikeness-0.2.2.dist-info/METADATA
druglikeness-0.2.2.dist-info/WHEEL
druglikeness-0.2.2.dist-info/top_level.txt
druglikeness-0.2.2.dist-info/RECORD
