Metadata-Version: 2.4
Name: druglikeness
Version: 0.2.2
Summary: AI-based drug-likeness prediction
Author-email: Seonghwan Seo <shwan0106@gmail.com>
Project-URL: Homepage, https://github.com/Seonghwan/drug-likeness
Keywords: rnn,drug-likeness
Classifier: Operating System :: OS Independent
Classifier: Programming Language :: Python
Classifier: Programming Language :: Python :: 3
Requires-Python: >=3.9
License-File: LICENSE
Requires-Dist: torch>=1.13.0
Requires-Dist: numpy
Requires-Dist: rdkit
Requires-Dist: gdown
Requires-Dist: tqdm
Provides-Extra: train
Requires-Dist: lightning; extra == "train"
Requires-Dist: wandb; extra == "train"
Provides-Extra: eval
Requires-Dist: matplotlib; extra == "eval"
Requires-Dist: seaborn; extra == "eval"
Dynamic: license-file
